image_fabio/__init__.py
image_fabio/processing/__init__.py
image_fabio/processing/combination.py
image_fabio/processing/tranformation.py
image_fabio/processing/transformation.py
image_fabio/utils/__init__.py
image_fabio/utils/io.py
image_fabio/utils/plot.py
image_fabio-0.0.4.dist-info/METADATA
image_fabio-0.0.4.dist-info/WHEEL
image_fabio-0.0.4.dist-info/top_level.txt
image_fabio-0.0.4.dist-info/RECORD
