Metadata-Version: 2.1
Name: image-fabio
Version: 0.0.4
Summary: Pacote para tratar imagens
Home-page: https://github.com/FabioTolentino19/image_fabio
Author: Fabio_Tolentino
Author-email: fabio.tolentino@uol.com.br
License: UNKNOWN
Platform: UNKNOWN
Requires-Python: >=3.0
Requires-Dist: matplotlib
Requires-Dist: numpy
Requires-Dist: scikit-image (>=0.16.1)
